README.md
setup.py
sequitur/__init__.py
sequitur/quick_train.py
sequitur/test.py
sequitur.egg-info/PKG-INFO
sequitur.egg-info/SOURCES.txt
sequitur.egg-info/dependency_links.txt
sequitur.egg-info/requires.txt
sequitur.egg-info/top_level.txt
sequitur/models/__init__.py
sequitur/models/conv_ae.py
sequitur/models/conv_lstm_ae.py
sequitur/models/linear_ae.py
sequitur/models/lstm_ae.py