Metadata-Version: 2.1
Name: sequitur
Version: 1.2.4
Summary: Autoencoders for sequential data
Home-page: https://github.com/shobrook/sequitur
Author: shobrook
Author-email: shobrookj@gmail.com
License: MIT
Keywords: sequitur,autoencoder,lstm,sequence,sequence-data,seq2seq
Platform: UNKNOWN
Requires-Python: >=3
